<?xml version="1.0" encoding="utf-8" ?>
<dwsync>
<file name="bibligrophy.html" server="www.michellefargher.com/coloradopoetscenter/" local="130731522375581927" remote="130731491400000000" Dst="2" />
<file name="commentary.html" server="www.michellefargher.com/coloradopoetscenter/" local="130731522375641934" remote="130731491400000000" Dst="2" />
<file name="index.html" server="www.michellefargher.com/coloradopoetscenter/" local="130731522375702159" remote="130731491400000000" Dst="2" />
<file name="nameless.html" server="www.michellefargher.com/coloradopoetscenter/" local="130731522375752262" remote="130731491400000000" Dst="2" />
<file name="readings.html" server="www.michellefargher.com/coloradopoetscenter/" local="130731522375812097" remote="130731491400000000" Dst="2" />
<file name="bibligrophy.html" server="www.findabrewery.com/coloradopoetscenter/" local="130923458036881718" remote="130923457800000000" Dst="1" />
<file name="commentary.html" server="www.findabrewery.com/coloradopoetscenter/" local="130923458036961941" remote="130923457800000000" Dst="1" />
<file name="index.html" server="www.findabrewery.com/coloradopoetscenter/" local="130923458037031728" remote="130923457800000000" Dst="1" />
<file name="nameless.html" server="www.findabrewery.com/coloradopoetscenter/" local="130923458037101896" remote="130923457800000000" Dst="1" />
<file name="readings.html" server="www.findabrewery.com/coloradopoetscenter/" local="130923458037171735" remote="130923457800000000" Dst="1" />
</dwsync>